fastpy/__init__.py
fastpy/constrain_solver.py
fastpy/core_language.py
fastpy/core_translator.py
fastpy/fastpy.py
fastpy/llvm_codegen.py
fastpy/pretty_printer.py
fastpy/type_inference.py
fastpy/type_mapping.py
fastpy/type_system.py
fastpy-0.1.1.dist-info/DESCRIPTION.rst
fastpy-0.1.1.dist-info/METADATA
fastpy-0.1.1.dist-info/RECORD
fastpy-0.1.1.dist-info/WHEEL
fastpy-0.1.1.dist-info/metadata.json
fastpy-0.1.1.dist-info/top_level.txt
