Metadata-Version: 2.0
Name: fastpy
Version: 0.1.1
Summary: LLVM JIT compiler as a function decorator
Home-page: https://github.com/tartavull/fastpy
Author: Ignacio Tartavull
Author-email: tartavull@gmail.com
License: MIT license
Keywords: fastpy
Platform: UNKNOWN
Classifier: Development Status :: 2 - Pre-Alpha
Classifier: Intended Audience :: Developers
Classifier: License :: OSI Approved :: MIT License
Classifier: Natural Language :: English
Classifier: Programming Language :: Python :: 2
Classifier: Programming Language :: Python :: 2.6
Classifier: Programming Language :: Python :: 2.7
Classifier: Programming Language :: Python :: 3
Classifier: Programming Language :: Python :: 3.3
Classifier: Programming Language :: Python :: 3.4
Classifier: Programming Language :: Python :: 3.5
Requires-Dist: llvmpy (>=0.11.1)
Requires-Dist: numpy (>=1.7.0)
